dinov2/__init__.py
dinov2/configs/__init__.py
dinov2/configs/ssl_default_config.yaml
dinov2/data/__init__.py
dinov2/data/adapters.py
dinov2/data/augmentations.py
dinov2/data/collate.py
dinov2/data/loaders.py
dinov2/data/masking.py
dinov2/data/samplers.py
dinov2/data/transforms.py
dinov2/data/datasets/__init__.py
dinov2/data/datasets/decoders.py
dinov2/data/datasets/extended.py
dinov2/data/datasets/image_net.py
dinov2/data/datasets/image_net_22k.py
dinov2/distributed/__init__.py
dinov2/eval/__init__.py
dinov2/eval/knn.py
dinov2/eval/linear.py
dinov2/eval/log_regression.py
dinov2/eval/metrics.py
dinov2/eval/setup.py
dinov2/eval/utils.py
dinov2/fsdp/__init__.py
dinov2/layers/__init__.py
dinov2/layers/attention.py
dinov2/layers/block.py
dinov2/layers/dino_head.py
dinov2/layers/drop_path.py
dinov2/layers/layer_scale.py
dinov2/layers/mlp.py
dinov2/layers/patch_embed.py
dinov2/layers/swiglu_ffn.py
dinov2/logging/__init__.py
dinov2/logging/helpers.py
dinov2/loss/__init__.py
dinov2/loss/dino_clstoken_loss.py
dinov2/loss/ibot_patch_loss.py
dinov2/loss/koleo_loss.py
dinov2/models/__init__.py
dinov2/models/vision_transformer.py
dinov2/run/__init__.py
dinov2/run/submit.py
dinov2/train/__init__.py
dinov2/train/ssl_meta_arch.py
dinov2/train/train.py
dinov2/utils/__init__.py
dinov2/utils/cluster.py
dinov2/utils/config.py
dinov2/utils/dtype.py
dinov2/utils/param_groups.py
dinov2/utils/utils.py
dinov2-0.0.1.dev2.dist-info/LICENSE
dinov2-0.0.1.dev2.dist-info/METADATA
dinov2-0.0.1.dev2.dist-info/WHEEL
dinov2-0.0.1.dev2.dist-info/dependency_links.txt
dinov2-0.0.1.dev2.dist-info/top_level.txt
dinov2-0.0.1.dev2.dist-info/RECORD
