Metadata-Version: 2.1
Name: dinov2
Version: 0.0.1.dev2
Summary: PyTorch code and models for the DINOv2 self-supervised learning method.
Home-page: https://github.com/Jack-Moo/DinoV2
Author: FAIR
License: CC-BY-NC
Platform: UNKNOWN
Classifier: Development Status :: 3 - Alpha
Classifier: Intended Audience :: Developers
Classifier: Intended Audience :: Science/Research
Classifier: License :: Other/Proprietary License
Classifier: Programming Language :: Python :: 3.9
Classifier: Topic :: Scientific/Engineering :: Artificial Intelligence
Classifier: Topic :: Software Development :: Libraries :: Python Modules
Requires-Python: >=3.9.0
License-File: LICENSE
Requires-Dist: torch (==2.0.0)
Requires-Dist: torchvision (==0.15.0)
Requires-Dist: omegaconf
Requires-Dist: torchmetrics (==0.10.3)
Requires-Dist: fvcore
Requires-Dist: iopath
Requires-Dist: xformers (==0.0.18)
Requires-Dist: submitit
Requires-Dist: cuml-cu11
Provides-Extra: dev
Requires-Dist: black (==22.6.0) ; extra == 'dev'
Requires-Dist: flake8 (==5.0.4) ; extra == 'dev'
Requires-Dist: pylint (==2.15.0) ; extra == 'dev'
